.gitignore
Bayesian-Inference.e4p
MANIFEST.in
README.md
distribute_setup.py
log.txt
requirements.txt
setup.cfg
setup.py
setup.py.bak
updocs.sh
BIP/__init__.py
BIP/__version__.py
BIP/logsetup.py
BIP.egg-info/PKG-INFO
BIP.egg-info/SOURCES.txt
BIP.egg-info/dependency_links.txt
BIP.egg-info/not-zip-safe
BIP.egg-info/requires.txt
BIP.egg-info/top_level.txt
BIP/Bayes/Melding.py
BIP/Bayes/Melding.py.before_restore_2010-04-21_14.39.58.289369
BIP/Bayes/PlotMeld.py
BIP/Bayes/__init__.py
BIP/Bayes/conjugate_priors.py.py
BIP/Bayes/lhs.py
BIP/Bayes/like.py
BIP/Bayes/Samplers/MCMC.pxd
BIP/Bayes/Samplers/MCMC.py
BIP/Bayes/Samplers/MCMC.py.before_restore_2010-04-21_14.39.58.289369
BIP/Bayes/Samplers/__init__.py
BIP/Bayes/general/__init__.py
BIP/Bayes/general/bayesvar.png
BIP/Bayes/general/bvariables.py
BIP/Bayes/general/like.pyc
BIP/Docs/Makefile
BIP/Docs/__init__.py
BIP/Docs/build/__init__.py
BIP/Docs/build/doctrees/API.doctree
BIP/Docs/build/doctrees/BIP.Bayes.Samplers.doctree
BIP/Docs/build/doctrees/BIP.Bayes.doctree
BIP/Docs/build/doctrees/BIP.doctree
BIP/Docs/build/doctrees/environment.pickle.before_restore_2010-04-21_14.39.58.289369
BIP/Docs/build/doctrees/index.doctree
BIP/Docs/build/doctrees/index.doctree.before_restore_2010-04-21_14.39.58.289369
BIP/Docs/build/doctrees/overview.doctree
BIP/Docs/build/doctrees/overview.doctree.before_restore_2010-04-21_14.39.58.289369
BIP/Docs/build/doctrees/paramest.doctree
BIP/Docs/build/doctrees/paramest.doctree.before_restore_2010-04-21_14.39.58.289369
BIP/Docs/build/doctrees/sde.doctree
BIP/Docs/build/html/.buildinfo
BIP/Docs/build/html/.buildinfo.before_restore_2010-04-21_14.39.58.289369
BIP/Docs/build/html/API.html
BIP/Docs/build/html/BIP.Bayes.Samplers.html
BIP/Docs/build/html/BIP.Bayes.html
BIP/Docs/build/html/BIP.html
BIP/Docs/build/html/__init__.py
BIP/Docs/build/html/genindex.html
BIP/Docs/build/html/genindex.html.before_restore_2010-04-21_14.39.58.289369
BIP/Docs/build/html/index.html
BIP/Docs/build/html/index.html.before_restore_2010-04-21_14.39.58.289369
BIP/Docs/build/html/objects.inv
BIP/Docs/build/html/objects.inv.before_restore_2010-04-21_14.39.58.289369
