Metadata-Version: 1.0
Name: BIP
Version: 0.6.16
Summary: Bayesian Inference Tools for Python
Home-page: https://github.com/fccoelho/bayesian-inference
Author: Flavio Codeco Coelho
Author-email: fccoelho@gmail.com
License: GPLv3
Platform: UNKNOWN
